football_analytics/__init__.py
football_analytics/__main__.py
football_analytics/config.py
football_analytics/scrapper.py
football_analytics/tasks/__init__.py
football_analytics/tasks/preprocess_data.py
football_analytics/tasks/scraping_extraction.py
football_analytics/tasks/scraping_utils.py
football_analytics/tasks/write_postgres_table.py
football_analytics/utils.py
football_analytics-0.2.0.dist-info/METADATA
football_analytics-0.2.0.dist-info/WHEEL
football_analytics-0.2.0.dist-info/entry_points.txt
football_analytics-0.2.0.dist-info/RECORD
