Metadata-Version: 2.1
Name: football-analytics
Version: 0.2.0
Summary: 
Author: Nelson Castro
Author-email: nelsoncastro@hotmail.fr
Requires-Python: >=3.9,<4.0
Classifier: Programming Language :: Python :: 3
Classifier: Programming Language :: Python :: 3.9
Classifier: Programming Language :: Python :: 3.10
Classifier: Programming Language :: Python :: 3.11
Classifier: Programming Language :: Python :: 3.12
Requires-Dist: beautifulsoup4 (>=4.12.3,<5.0.0)
Requires-Dist: fastapi (>=0.109.2,<0.110.0)
Requires-Dist: lxml (>=5.1.0,<6.0.0)
Requires-Dist: pandas (>=2.2.0,<3.0.0)
Requires-Dist: psycopg2-binary (>=2.9.9,<3.0.0)
Requires-Dist: requests (>=2.31.0,<3.0.0)
Requires-Dist: sqlalchemy (>=2.0.27,<3.0.0)
Requires-Dist: typer (>=0.12.3,<0.13.0)
Requires-Dist: uvicorn[standard] (>=0.27.0.post1,<0.28.0)
